category_encoders/__init__.py
category_encoders/backward_difference.py
category_encoders/base_contrast_encoder.py
category_encoders/basen.py
category_encoders/binary.py
category_encoders/cat_boost.py
category_encoders/count.py
category_encoders/glmm.py
category_encoders/gray.py
category_encoders/hashing.py
category_encoders/helmert.py
category_encoders/james_stein.py
category_encoders/leave_one_out.py
category_encoders/m_estimate.py
category_encoders/one_hot.py
category_encoders/ordinal.py
category_encoders/polynomial.py
category_encoders/quantile_encoder.py
category_encoders/rankhot.py
category_encoders/sum_coding.py
category_encoders/target_encoder.py
category_encoders/utils.py
category_encoders/woe.py
category_encoders/wrapper.py
category_encoders/datasets/__init__.py
category_encoders/datasets/_base.py
category_encoders/datasets/data/compass.csv
category_encoders/datasets/data/postcode_dataset_100.csv
category_encoders-2.6.4.dist-info/LICENSE.md
category_encoders-2.6.4.dist-info/METADATA
category_encoders-2.6.4.dist-info/WHEEL
category_encoders-2.6.4.dist-info/top_level.txt
category_encoders-2.6.4.dist-info/RECORD
