Metadata-Version: 2.1
Name: category_encoders
Version: 2.6.4
Summary: A collection of sklearn transformers to encode categorical variables as numeric
Home-page: https://github.com/scikit-learn-contrib/category_encoders
Author: Will McGinnis
Author-email: will@pedalwrencher.com
License: BSD
Download-URL: https://github.com/scikit-learn-contrib/category_encoders/tarball/2.6.4
Keywords: python data science machine learning pandas sklearn
Platform: UNKNOWN
Classifier: Development Status :: 3 - Alpha
Classifier: Intended Audience :: Developers
Classifier: Programming Language :: Python :: 3
